plan4past/__init__.py
plan4past/__main__.py
plan4past/compiler.py
plan4past/helpers/__init__.py
plan4past/helpers/utils.py
plan4past/utils/__init__.py
plan4past/utils/atoms_visitor.py
plan4past/utils/derived_visitor.py
plan4past/utils/mapping_parser.py
plan4past/utils/predicates_visitor.py
plan4past/utils/rewrite_formula_visitor.py
plan4past/utils/val_predicates_visitor.py
plan4past-0.1.0.dist-info/LICENSE
plan4past-0.1.0.dist-info/METADATA
plan4past-0.1.0.dist-info/WHEEL
plan4past-0.1.0.dist-info/entry_points.txt
plan4past-0.1.0.dist-info/RECORD
