Metadata-Version: 2.1
Name: plan4past
Version: 0.1.0
Summary: Classical and FOND Planning for Pure-Past Linear Temporal Logic Goals
Home-page: https://whitemech.github.io/plan4past
License: LGPLv3+ license
Keywords: automated planning,temporally extended goals,pure-past linear temporal logic
Author: Luigi Bonassi
Author-email: luigi.bonassi@unibs.it
Requires-Python: >=3.8.1,<4.0
Classifier: Development Status :: 2 - Pre-Alpha
Classifier: Intended Audience :: Developers
Classifier: License :: OSI Approved :: GNU Lesser General Public License v3 or later (LGPLv3+)
Classifier: License :: Other/Proprietary License
Classifier: Natural Language :: English
Classifier: Programming Language :: Python :: 3
Classifier: Programming Language :: Python :: 3.9
Classifier: Programming Language :: Python :: 3.10
Classifier: Programming Language :: Python :: 3.11
Classifier: Programming Language :: Python :: 3.8
Requires-Dist: click (>=8.1.3,<9.0.0)
Requires-Dist: pddl (>=0.3.1,<0.4.0)
Requires-Dist: pylogics (>=0.2.1,<0.3.0)
Project-URL: Bug Tracker, https://github.com/whitemech/plan4past/issues
Project-URL: Documentation, https://whitemech.github.io/plan4past
Project-URL: Pull Requests, https://github.com/whitemech/plan4past/pulls
Project-URL: Repository, https://github.com/whitemech/plan4past.git
